[
    {
        "Word": "qanxxiis",
        "POS": "transitive verb",
        "Meaning": "cut; hew"
    },
    {
        "Word": "qachchiis",
        "POS": "transitive verb",
        "Meaning": "tie; fasten; buckle; bind"
    },
    {
        "Word": "naagiis",
        "POS": "transitive verb",
        "Meaning": "wait for, just a moment, wait a moment"
    },
    {
        "Word": "essiis",
        "POS": "transitive verb",
        "Meaning": "stop; cease"
    },
    {
        "Word": "deriya",
        "POS": "noun",
        "Meaning": "mountain"
    }
]